{"id":"0500f1af-2aeb-4910-b18d-529db807e69d", "user_id":"kanhaiya_vaccinator", "user_name":"kanhaiya_vaccinator", "user_type":"receptionist", "lname":"Singh", "fname":"kanhaiya", "email":"kanhaiyasinghvaccinator@yopmail.com", "mobile_number":"+448987678987", "dob":"", "gender":"", "address1":"", "address2":"", "address3":"", "city":"", "state":"", "zip":"", "country":"", "countryFlag":{"name":"United Kingdom", "iso2":"gb", "dial_code":"+44"}, "site_ids":["76a24d65-cfc8-47a9-9c58-b6c7080756e1"], "is_active":true, "create_time":"2021-08-02T10:37:48.687Z", "modify_time":"2021-10-01T05:10:44.351Z", "provider_id":"bf504ea1-4b30-463d-87e3-70f263eaa9be"}