{"id":"5090178a-4641-4a03-9342-8e9f39267d92", "provider_id":"bf504ea1-4b30-463d-87e3-70f263eaa9be", "user_name":"front_end_va_3", "user_type":"vaccinator", "lname":"Front End", "fname":"Vaccinator", "email":"frontend001@yopmail.com", "mobile_number":"+12014222730", "dob":"1970-01-01", "gender":"Male", "address1":"123 Main St", "address2":"", "address3":"", "city":"New York City", "state":"NY", "zip":"1234", "county":"New York", "country":"US", "site_ids":[], "is_active":true, "create_time":"2021-12-24T05:38:22.244Z", "modify_time":"2021-12-24T05:38:22.244Z"}