{"id":"80ebfa83-2596-4586-8f62-2362f0e01c24", "user_id":"Garryone_reecep", "user_name":"Garryone_reecep", "user_type":"receptionist", "lname":"RecepUp", "fname":"Garryone", "email":"Garryone.recep@yopmail.com", "mobile_number":"+17878788083", "dob":"", "gender":"Male", "address1":"", "address2":"", "address3":"", "state":"", "zip":"", "county":"", "country":"", "countryFlag":null, "provider_id":"be3aae15-9c31-4652-8746-5e0995193177", "site_ids":["b7c64e5c-eaa7-475f-bbbf-f382b6a23967"], "is_active":true, "create_time":"2021-12-06T08:51:18.063Z", "modify_time":"2021-12-06T08:51:32.707Z"}