{"id":"d9571f90-79d4-4317-908c-bb7df3c54a81", "user_id":"sunil_site", "user_name":"sunil_site", "user_type":"site_admin", "lname":"site", "fname":"Apollo", "email":"sunil.saptal@trigyn.com", "mobile_number":"+918097131359", "dob":"", "gender":"Male", "address1":"", "address2":"", "address3":"", "state":"", "zip":"", "county":"", "country":"", "provider_id":"bf504ea1-4b30-463d-87e3-70f263eaa9be", "site_ids":["c40a7445-c208-43c8-a978-1a4ea70ecec6"], "is_active":true, "create_time":"2021-07-16T05:52:37.657Z", "modify_time":"2021-07-20T13:34:20.876Z", "is_disabled":false}