{"user_id":"", "fname":"Carmina", "lname":"Windous", "dob":"1966-09-01", "gender":"Male", "email":"", "mobile_number":"", "address1":"511 Grayhawk Crossing", "address2":"", "address3":"", "city":"Union", "state":"NJ", "zip":"", "county":"Union", "country":"United States", "races":["White"], "ethnicity":"Not Hispanic or Latino", "classification":"NJIIS", "is_activated":false, "registered_by_id":"11ee0d91-d217-4f9b-a0ab-293b267039c8", "registered_date":"2021-11-22", "id":"33b73ffc-17aa-4b22-b0a3-196d4bbdf712", "is_active":true, "create_time":"2021-11-22T22:08:49.030Z", "modify_time":"2021-11-22T22:08:49.030Z", "concatenated_races":"White"}