{"address1":"Green House1", "address2":"Street1", "address3":"Unit - 22", "city":"New York", "country":"US", "county":"New York", "dob":"1986-08-11", "email":"deepak.shetty@trigyn.com", "fname":"David S", "gender":"Male", "home_number":"", "lname":"Kinley", "mobile_number":"+919967829086", "state":"New York", "static_questionnaire_answers":[{"question_id":"3", "question_text":"Insurance", "answers":["Bima"]}, {"question_id":"4", "question_text":"Insurance Provider Name", "answers":["LIC"]}, {"question_id":"5", "question_text":"Medical Group Number", "answers":["4567"]}, {"question_id":"6", "question_text":"Medical ID", "answers":["8768"]}, {"question_id":"1", "question_text":"Which of the following best describes your ethnic group? *", "answers":["Hispanic or Latino"]}, {"question_id":"2", "question_text":"Which of the following best describes your race? Please select all that apply? *", "answers":["American Indian"]}, {"question_id":"7", "question_text":"Select all that apply", "answers":["I work in a patient-facing healthcare setting or a congregate living setting."]}, {"question_id":"12", "question_text":" Have you ever had any of the following medical conditions? - Asthama(moderate to severe) - Cancer - Cerebrovascular disease - Chronic Kidney Disease - Chronic obstructive pulmonary disease (COPD) - Cystic fibrosis - Down Syndrome - Heart conditions, such as coronary artery disease or cardiomyopathies - Hypertension or high blood pressure - Immunocompromised state (weakened immune system) - Liver disease - Neurologic conditions, (such as dementia) - Nicotine/smoking addiction - Obesity - Overweight - Pulmonary fibrosis (damaged or scarred lung tissues) - Sickle cell disease - Thalassemia (type of blood disorder) - Type 1 diabetes mellitus - Type 2 diabetes mellitus.", "answers":["No"]}, {"question_id":"8", "question_text":"Prescription, over-the- counter medications, dietary supplements, or herbal remedies being taken at the time of Vaccination.", "answers":[""]}, {"question_id":"9", "question_text":"Allergies to medications, food, or other products:", "answers":["No All"]}, {"question_id":"10", "question_text":"Other illnesses at the time of vaccination and up to one month", "answers":[""]}, {"question_id":"11", "question_text":"Chronic or long-standing health conditions prior", "answers":["No cho"]}], "zip":"10001", "countryFlag":{"name":"India (भारत)", "iso2":"in", "dial_code":"+91"}, "ethnicity":"Hispanic or Latino", "races":["American Indian"], "id":"41163918-9558-4930-b52e-538ee2e6b6b3", "is_activated":true, "user_id":"+919967829086", "registered_date":"2021-06-05", "is_active":true, "create_time":"2021-06-05T10:46:32.800Z", "modify_time":"2021-10-05T11:45:22.485Z", "concatenated_races":"American Indian", "recipient_facts":[{"RecipientFact":{"material_id":"08756daa-e635-4609-bf06-e14c7a6f2a6b", "material_batch_id":"13c8c548-d3fa-412a-a042-afc35d806f12", "batch_no":"MD001", "dose_in_series":1, "dose_date":"2021-06-05T10:59:36.705Z", "status":"completed", "visit_id":"38b81c5e-8fc3-4fe2-9ba3-65d6d4ee32b3", "site_id":"fbb20ba7-42d3-435c-88cb-01f22c041f67", "ticket_number":"A08R00", "material_category_id":"865ab47e-fab1-4871-98e7-5306c013ec10", "material_category_name":"Covid 19"}}, {"RecipientFact":{"material_id":"08756daa-e635-4609-bf06-e14c7a6f2a6b", "material_batch_id":"13c8c548-d3fa-412a-a042-afc35d806f12", "batch_no":"MD001", "dose_in_series":2, "dose_date":"2021-07-03T11:04:11.113Z", "status":"completed", "visit_id":"8b0c1bc6-30be-41ce-b587-a5b6653843ed", "site_id":"fbb20ba7-42d3-435c-88cb-01f22c041f67", "ticket_number":"BML8A8", "material_category_id":"865ab47e-fab1-4871-98e7-5306c013ec10", "material_category_name":"Covid 19"}}], "administered_doses":["08756daa-e635-4609-bf06-e14c7a6f2a6b_DOSE_1", "08756daa-e635-4609-bf06-e14c7a6f2a6b_DOSE_2"], "employment_types":["I work in a patient-facing healthcare setting or a congregate living setting."], "medical_condition":"No"}