{"fname":"Sean", "lname":"taylor", "email":"Sean.taylor@yopmail.com", "mobile_number":"+1", "home_number":"2564567567", "dob":"1987-08-15", "gender":"", "address1":"", "address2":"", "address3":"", "zip":"", "city":"", "state":"", "country":"US", "county":"", "ethnicity":"Not Hispanic or Latino", "races":["Asian"], "countryFlag":{"name":"United States", "iso2":"us", "dial_code":"+1"}, "static_questionnaire_answers":[{"question_id":"3", "question_text":"Insurance", "answers":[""]}, {"question_id":"4", "question_text":"Insurance Provider Name", "answers":[""]}, {"question_id":"5", "question_text":"Medical Group Number", "answers":[""]}, {"question_id":"6", "question_text":"Medical ID", "answers":[""]}, {"question_id":"1", "question_text":"Which of the following best describes your ethnic group? *", "answers":["Not Hispanic or Latino"]}, {"question_id":"2", "question_text":"Which of the following best describes your race? Please select all that apply? *", "answers":["Asian"]}, {"question_id":"12", "question_text":" Have you ever had any of the following medical conditions? - Asthama(moderate to severe) - Cancer - Cerebrovascular disease - Chronic Kidney Disease - Chronic obstructive pulmonary disease (COPD) - Cystic fibrosis - Down Syndrome - Heart conditions, such as coronary artery disease or cardiomyopathies - Hypertension or high blood pressure - Immunocompromised state (weakened immune system) - Liver disease - Neurologic conditions, (such as dementia) - Nicotine/smoking addiction - Obesity - Overweight - Pulmonary fibrosis (damaged or scarred lung tissues) - Sickle cell disease - Thalassemia (type of blood disorder) - Type 1 diabetes mellitus - Type 2 diabetes mellitus.", "answers":[""]}, {"question_id":"7", "question_text":"Select all that apply", "answers":[]}, {"question_id":"8", "question_text":"Prescription, over-the- counter medications, dietary supplements, or herbal remedies being taken at the time of Vaccination.", "answers":[]}, {"question_id":"9", "question_text":"Allergies to medications, food, or other products:", "answers":[""]}, {"question_id":"10", "question_text":"Other illnesses at the time of vaccination and up to one month", "answers":[]}, {"question_id":"11", "question_text":"Chronic or long-standing health conditions prior", "answers":[""]}], "medical_condition":"", "employment_types":[], "is_activated":false, "registered_date":"2021-10-07", "registered_by_id":"47b143fa-cedd-4dc8-b6a6-a4f673abe488", "id":"4c366cea-a39b-4a59-afef-7908ee67e647", "is_active":true, "create_time":"2021-10-07T06:43:56.829Z", "modify_time":"2021-10-07T07:27:45.211Z", "concatenated_races":"Asian", "recipient_facts":[{"RecipientFact":{"dose_in_series":1, "dose_date":"2021-08-18T03:15:00", "status":"completed", "visit_id":"22c323fd-1362-496f-81f5-8146f887e5d8", "site_id":"418246d7-d21d-4f02-a003-d7df61a35a4b", "material_id":"ac8f5cc5-f2e7-4dee-a897-bfe115e7e7bf", "material_category_id":"865ab47e-fab1-4871-98e7-5306c013ec10", "batch_no":"l354", "isExternalVisit":true, "ticket_number":"S345345"}}, {"RecipientFact":{"dose_in_series":2, "dose_date":"2021-09-30T05:25:00", "status":"completed", "visit_id":"a7d87f7c-e891-4946-8306-56fd6fde1b64", "site_id":"418246d7-d21d-4f02-a003-d7df61a35a4b", "material_id":"ac8f5cc5-f2e7-4dee-a897-bfe115e7e7bf", "material_category_id":"865ab47e-fab1-4871-98e7-5306c013ec10", "batch_no":"l243", "isExternalVisit":true, "ticket_number":"S234"}}], "administered_doses":["ac8f5cc5-f2e7-4dee-a897-bfe115e7e7bf_DOSE_1", "ac8f5cc5-f2e7-4dee-a897-bfe115e7e7bf_DOSE_2", "ac8f5cc5-f2e7-4dee-a897-bfe115e7e7bf_DOSE_1"]}