{"user_id":"+11233602107", "fname":"walker3", "lname":"Kenedy", "dob":"2003-08-15", "gender":"Male", "email":"Kenedy.walker3@yopmail.com", "mobile_number":"+11233602107", "address1":"113 high view", "address2":"", "address3":"", "city":"New York City", "state":"NY", "zip":"10001", "county":"New York", "country":"United States", "races":["Black or African American"], "ethnicity":"Hispanic or Latino", "classification":"1B", "is_activated":false, "registered_date":"2021-06-14", "id":"5a549aa6-bd04-40d9-9781-f5f2270015c2", "is_active":true, "create_time":"2021-06-14T14:50:00.759Z", "modify_time":"2021-06-14T14:50:00.759Z", "concatenated_races":"Black or African American"}