{"fname":"David", "lname":"johny", "email":"", "mobile_number":"+1", "home_number":"8768768766", "dob":"1986-06-25", "gender":"", "address1":"", "address2":"", "address3":"", "zip":"", "city":"", "state":"", "country":"US", "county":"", "ethnicity":"Not Hispanic or Latino", "races":["Asian", "Black or African American"], "countryFlag":{"name":"United States", "iso2":"us", "dial_code":"+1"}, "static_questionnaire_answers":[{"question_id":"3", "question_text":"Insurance", "answers":[""]}, {"question_id":"4", "question_text":"Insurance Provider Name", "answers":[""]}, {"question_id":"5", "question_text":"Medical Group Number", "answers":[""]}, {"question_id":"6", "question_text":"Medical ID", "answers":[""]}, {"question_id":"1", "question_text":"Which of the following best describes your ethnic group? *", "answers":["Not Hispanic or Latino"]}, {"question_id":"2", "question_text":"Which of the following best describes your race? Please select all that apply? *", "answers":["Asian", "Black or African American"]}, {"question_id":"12", "question_text":" Have you ever had any of the following medical conditions? - Asthama(moderate to severe) - Cancer - Cerebrovascular disease - Chronic Kidney Disease - Chronic obstructive pulmonary disease (COPD) - Cystic fibrosis - Down Syndrome - Heart conditions, such as coronary artery disease or cardiomyopathies - Hypertension or high blood pressure - Immunocompromised state (weakened immune system) - Liver disease - Neurologic conditions, (such as dementia) - Nicotine/smoking addiction - Obesity - Overweight - Pulmonary fibrosis (damaged or scarred lung tissues) - Sickle cell disease - Thalassemia (type of blood disorder) - Type 1 diabetes mellitus - Type 2 diabetes mellitus.", "answers":[""]}, {"question_id":"7", "question_text":"Select all that apply", "answers":[]}, {"question_id":"8", "question_text":"Prescription, over-the- counter medications, dietary supplements, or herbal remedies being taken at the time of Vaccination.", "answers":[]}, {"question_id":"9", "question_text":"Allergies to medications, food, or other products:", "answers":[""]}, {"question_id":"10", "question_text":"Other illnesses at the time of vaccination and up to one month", "answers":[]}, {"question_id":"11", "question_text":"Chronic or long-standing health conditions prior", "answers":[""]}], "is_activated":false, "registered_date":"2021-06-04", "id":"5b3ee7c4-3bb6-4474-a86b-fd7cdf5dc465", "is_active":true, "create_time":"2021-06-04T05:31:35.432Z", "modify_time":"2021-10-05T11:45:36.499Z", "concatenated_races":"Asian, Black or African American", "recipient_facts":[{"RecipientFact":{"material_id":"08756daa-e635-4609-bf06-e14c7a6f2a6b", "material_batch_id":"13c8c548-d3fa-412a-a042-afc35d806f12", "batch_no":"MD001", "dose_in_series":1, "dose_date":"2021-06-04T05:51:12.824Z", "status":"completed", "visit_id":"5660bfb9-cb01-4a0a-8338-afe5b77a9c63", "site_id":"fbb20ba7-42d3-435c-88cb-01f22c041f67", "ticket_number":"9ZM8TC", "material_category_id":"865ab47e-fab1-4871-98e7-5306c013ec10", "material_category_name":"Covid 19"}}, {"RecipientFact":{"material_id":"08756daa-e635-4609-bf06-e14c7a6f2a6b", "material_batch_id":"13c8c548-d3fa-412a-a042-afc35d806f12", "batch_no":"MD001", "dose_in_series":2, "dose_date":"2021-08-06T07:11:57.939Z", "status":"completed", "visit_id":"736313c9-1e0d-4c77-9d4e-7ed080ee758f", "site_id":"fbb20ba7-42d3-435c-88cb-01f22c041f67", "ticket_number":"DBVDKX", "material_category_id":"865ab47e-fab1-4871-98e7-5306c013ec10", "material_category_name":"Covid 19"}}], "administered_doses":["08756daa-e635-4609-bf06-e14c7a6f2a6b_DOSE_1", "08756daa-e635-4609-bf06-e14c7a6f2a6b_DOSE_2"], "medical_condition":"", "employment_types":[]}