{"user_id":"+11233608879", "fname":"Ken", "lname":"Dalton", "dob":"1986-07-24", "gender":"Male", "email":"sam.dalton@yopmail.com", "mobile_number":"+11233608879", "address1":"113 high view", "address2":"", "address3":"", "city":"New York City", "state":"NY", "zip":"10001", "county":"New York", "country":"United States", "races":["Black or African American"], "ethnicity":"Hispanic or Latino", "classification":"1B", "is_activated":false, "registered_date":"2021-07-05", "id":"70169662-29f8-47fe-bdc1-894e8d9fb339", "is_active":true, "create_time":"2021-07-05T12:40:01.912Z", "modify_time":"2021-10-05T11:45:48.481Z", "concatenated_races":"Black or African American", "recipient_facts":[{"RecipientFact":{"dose_in_series":2, "dose_date":"2021-07-22T09:00:00", "status":"completed", "visit_id":"d0947802-6c1c-4af0-86b1-6b15c0681df6", "site_id":"4605c60e-a699-42d0-901b-62b14b3a57ba", "material_id":"08756daa-e635-4609-bf06-e14c7a6f2a6b", "ticket_number":"BXWW7K", "material_category_id":"865ab47e-fab1-4871-98e7-5306c013ec10", "material_category_name":"Covid 19"}}, {"RecipientFact":{"dose_in_series":1, "dose_date":"2021-07-05T09:15:00", "status":"completed", "visit_id":"cec596c4-9873-4848-a0ce-0e9988d3e821", "site_id":"4605c60e-a699-42d0-901b-62b14b3a57ba", "material_id":"08756daa-e635-4609-bf06-e14c7a6f2a6b", "ticket_number":"BNSIXF", "material_category_id":"865ab47e-fab1-4871-98e7-5306c013ec10", "material_category_name":"Covid 19"}}], "administered_doses":["08756daa-e635-4609-bf06-e14c7a6f2a6b_DOSE_2", "08756daa-e635-4609-bf06-e14c7a6f2a6b_DOSE_1"]}