{"user_id":"+11233607773", "fname":"Tom", "lname":"Gress", "dob":"1986-07-24", "gender":"Male", "email":"tom.gress@yopmail.com", "mobile_number":"+11233607773", "address1":"113 high view", "address2":"", "address3":"", "city":"New York City", "state":"NY", "zip":"10001", "county":"New York", "country":"United States", "races":["Black or African American"], "ethnicity":"Hispanic or Latino", "classification":"1B", "is_activated":false, "registered_by_id":"37c207fa-f4f9-48ff-830d-90a5ec17de71", "registered_date":"2021-07-23", "id":"75d2b3c0-c76b-4b71-aa68-041a2441ef6f", "is_active":true, "create_time":"2021-07-23T07:28:08.767Z", "modify_time":"2021-07-23T07:28:08.767Z", "concatenated_races":"Black or African American"}