{"user_id":"+11233603943", "fname":"Harry3", "lname":"martin", "dob":"1986-06-02", "gender":"Male", "email":"Harry3.martin@yopmail.com", "mobile_number":"+11233603943", "address1":"113 high view", "address2":"", "address3":"", "city":"New York City", "state":"NY", "zip":"10001", "county":"New York", "country":"United States", "races":["Black or African American"], "ethnicity":"Hispanic or Latino", "classification":"1B", "is_activated":false, "registered_date":"2021-06-07", "id":"b2d8d32b-3120-4082-9eaa-48694a38ebde", "is_active":true, "create_time":"2021-06-07T10:59:41.085Z", "modify_time":"2021-10-05T11:46:25.613Z", "concatenated_races":"Black or African American", "recipient_facts":[{"RecipientFact":{"dose_in_series":1, "dose_date":"2021-05-05T10:00:00", "status":"completed", "visit_id":"8ded4fba-640a-45e6-a60e-74f7ce418471", "site_id":"fbb20ba7-42d3-435c-88cb-01f22c041f67", "material_id":"08756daa-e635-4609-bf06-e14c7a6f2a6b", "batch_no":"L234234", "isExternalVisit":true, "ticket_number":"S24234", "material_category_id":"865ab47e-fab1-4871-98e7-5306c013ec10", "material_category_name":"Covid 19"}}], "administered_doses":["08756daa-e635-4609-bf06-e14c7a6f2a6b_DOSE_1"]}