{"user_id":"+11233607762", "fname":"Ken", "lname":"Ted", "dob":"1986-07-24", "gender":"Male", "email":"ken.ted@yopmail.com", "mobile_number":"+11233607762", "address1":"113 high view", "address2":"", "address3":"", "city":"New York City", "state":"NY", "zip":"10001", "county":"New York", "country":"United States", "races":["Black or African American"], "ethnicity":"Hispanic or Latino", "classification":"1B", "is_activated":false, "registered_by_id":"2ec432ad-37a9-439e-9113-2e626e3e424b", "registered_date":"2021-07-22", "id":"c6f063ed-6f0b-4710-82fe-53c5e8681031", "is_active":false, "create_time":"2021-07-22T09:19:52.436Z", "modify_time":"2021-07-26T06:15:27.144Z", "concatenated_races":"Black or African American", "is_disabled":true, "recipient_facts":[], "administered_doses":[]}